{
  "sku": "126718",
  "name": "Osprey Women's Eja 48 Pack",
  "image": "https://www.rei.com/media/74c4b8a5-447e-428a-b316-9502f096ed73",
  "buy_link": "https://www.avantlink.com/click.php?tt=pl&ti=115&pw=179682&mi=16517&pt=3&pri=633272",
  "price": "200.00",
  "long_description": "A women-specific pack for quick overnights and long thru-hikes, the ultralight Osprey Eja 48 pack is an ideal partner for planning your next escape to wildflower-dotted meadows and icy alpine streams.",
  "gender": "female",
  "age_group": "adult",
  "category": "Camping And Hiking",
  "sub_category": "Hiking Backpacks",
  "product_group": "Backpacking Packs",
  "load": {
    "low": 20,
    "high": 40
  },
  "best_used_for": "Backpacking",
  "fit_torso_in": "XS: 14 - 17 inches, S: 16 - 19 inches",
  "fit_waist_in": "XS: 24 - 45 inches, S: 24 - 45 inches",
  "materials": "100-denier high-tenacity nylon/210-denier high-tenacity nylon",
  "dimensions": "30 x 16 x 14 inches",
  "colors": {
    "data": [
      "Equinox Blue"
    ],
    "raw": "Equinox Blue"
  },
  "sizes": {
    "data": [
      "XS",
      "S"
    ],
    "raw": "XS, S"
  },
  "volume": {
    "data": [
      {
        "key": "XS",
        "val": 42,
        "raw": "42 liters"
      },
      {
        "key": "S",
        "val": 45,
        "raw": "45 liters"
      }
    ],
    "unit": "liters",
    "raw": "XS: 42 liters, S: 45 liters"
  },
  "weight": {
    "data": [
      {
        "key": "XS",
        "val": 40,
        "raw": "2 lbs. 8 oz."
      },
      {
        "key": "S",
        "val": 41,
        "raw": "2 lbs. 9 oz."
      }
    ],
    "unit": "oz",
    "raw": "XS: 2 lbs. 8 oz., S: 2 lbs. 9 oz."
  },
  "price_history": {
    "rei": {
      "data": [
        {
          "t": "2018-01-11",
          "y": "200.00"
        },
        {
          "t": "2018-08-25",
          "y": "149.99"
        },
        {
          "t": "2018-09-05",
          "y": "200.00"
        },
        {
          "t": "2019-11-16",
          "y": "149.99"
        },
        {
          "t": "2019-11-27",
          "y": "200.00"
        },
        {
          "t": "2020-08-28",
          "y": "149.99"
        },
        {
          "t": "2020-09-09",
          "y": "200.00"
        },
        {
          "t": "2021-02-06",
          "y": "149.93"
        },
        {
          "t": "2021-02-07",
          "y": "200.00"
        },
        {
          "t": "2021-02-08",
          "y": "149.93"
        },
        {
          "t": "2021-02-09",
          "y": "200.00"
        },
        {
          "t": "2021-02-25",
          "y": "149.93"
        },
        {
          "t": "2021-02-26",
          "y": "200.00"
        },
        {
          "t": "2021-03-17",
          "y": "149.93"
        },
        {
          "t": "2021-03-18",
          "y": "200.00"
        }
      ],
      "labels": [
        "2018-01-11",
        "2018-08-25",
        "2018-09-05",
        "2019-11-16",
        "2019-11-27",
        "2020-08-28",
        "2020-09-09",
        "2021-02-06",
        "2021-02-07",
        "2021-02-08",
        "2021-02-09",
        "2021-02-25",
        "2021-02-26",
        "2021-03-17",
        "2021-03-18"
      ]
    },
    "backcountry": {
      "data": [
        {
          "t": "2018-02-03",
          "y": "200.00"
        },
        {
          "t": "2018-05-10",
          "y": "160.00"
        },
        {
          "t": "2018-05-13",
          "y": "200.00"
        },
        {
          "t": "2018-06-28",
          "y": "160.00"
        },
        {
          "t": "2018-07-05",
          "y": "200.00"
        },
        {
          "t": "2018-07-06",
          "y": "160.00"
        },
        {
          "t": "2018-07-11",
          "y": "200.00"
        },
        {
          "t": "2018-07-14",
          "y": "160.00"
        },
        {
          "t": "2018-07-18",
          "y": "200.00"
        },
        {
          "t": "2018-07-28",
          "y": "160.00"
        },
        {
          "t": "2018-08-01",
          "y": "200.00"
        },
        {
          "t": "2018-08-24",
          "y": "150.00"
        },
        {
          "t": "2018-09-04",
          "y": "200.00"
        },
        {
          "t": "2018-11-17",
          "y": "149.95"
        },
        {
          "t": "2018-11-28",
          "y": "200.00"
        },
        {
          "t": "2018-12-19",
          "y": "160.00"
        },
        {
          "t": "2018-12-20",
          "y": "200.00"
        },
        {
          "t": "2019-08-21",
          "y": "199.95"
        },
        {
          "t": "2019-11-15",
          "y": "149.95"
        },
        {
          "t": "2019-11-27",
          "y": "199.95"
        },
        {
          "t": "2020-01-01",
          "y": "200.00"
        },
        {
          "t": "2020-01-14",
          "y": "199.95"
        },
        {
          "t": "2020-03-20",
          "y": "149.96"
        },
        {
          "t": "2020-03-21",
          "y": "199.95"
        },
        {
          "t": "2020-07-01",
          "y": "200.00"
        },
        {
          "t": "2020-08-28",
          "y": "149.95"
        },
        {
          "t": "2020-09-08",
          "y": "200.00"
        },
        {
          "t": "2021-01-01",
          "y": "199.95"
        },
        {
          "t": "2021-03-10",
          "y": "160.00"
        },
        {
          "t": "2021-03-16",
          "y": "150.00"
        },
        {
          "t": "2021-04-02",
          "y": "160.00"
        }
      ],
      "labels": [
        "2018-02-03",
        "2018-05-10",
        "2018-05-13",
        "2018-06-28",
        "2018-07-05",
        "2018-07-06",
        "2018-07-11",
        "2018-07-14",
        "2018-07-18",
        "2018-07-28",
        "2018-08-01",
        "2018-08-24",
        "2018-09-04",
        "2018-11-17",
        "2018-11-28",
        "2018-12-19",
        "2018-12-20",
        "2019-08-21",
        "2019-11-15",
        "2019-11-27",
        "2020-01-01",
        "2020-01-14",
        "2020-03-20",
        "2020-03-21",
        "2020-07-01",
        "2020-08-28",
        "2020-09-08",
        "2021-01-01",
        "2021-03-10",
        "2021-03-16",
        "2021-04-02"
      ]
    },
    "osprey": {
      "data": [
        {
          "t": "2020-01-14",
          "y": "200.00"
        },
        {
          "t": "2020-08-28",
          "y": "149.95"
        },
        {
          "t": "2020-09-09",
          "y": "200.00"
        }
      ],
      "labels": [
        "2020-01-14",
        "2020-08-28",
        "2020-09-09"
      ]
    }
  },
  "purchase_info": {
    "rei": {
      "retail_price": "200.00",
      "sale_price": "200.00",
      "buy_link": "https://www.avantlink.com/click.php?tt=pl&ti=115&pw=179682&mi=16517&pt=3&pri=633272",
      "dividend": "$20.00"
    },
    "backcountry": {
      "retail_price": "200.00",
      "sale_price": "160.00",
      "buy_link": "https://www.avantlink.com/click.php?tt=pl&ti=52&pw=179682&mi=16517&pt=3&pri=1216623",
      "availability": true
    },
    "osprey": {
      "retail_price": "200.00",
      "sale_price": "200.00",
      "buy_link": "https://www.avantlink.com/click.php?tt=pl&ti=6969&pw=179682&mi=16517&pt=3&pri=231",
      "availability": true,
      "stock": "26"
    }
  }
}
